<?xml version="1.0" encoding="utf-8" ?>
<Defs>
	<!-- .31 Caliber -->
	
	<CombatExtended.AmmoSetDef>
		<defName>AmmoSet_MusketBall_31Caliber_Pistol</defName>
		<label>.31 caliber ball</label>
		<ammoTypes>
			<Ammo_MusketBall>Bullet_31CaliberBall_Pistol</Ammo_MusketBall>
		</ammoTypes>
	</CombatExtended.AmmoSetDef>

	<ThingDef ParentName="MusketBallBullet">
		<defName>Bullet_31CaliberBall_Pistol</defName>
		<label>.31 caliber ball</label>
		<projectile Class="CombatExtended.ProjectilePropertiesCE">
			<speed>45</speed>	
			<damageAmountBase>8</damageAmountBase>		
			<armorPenetrationSharp>2.5</armorPenetrationSharp>
			<armorPenetrationBlunt>5</armorPenetrationBlunt>				
		</projectile>
	</ThingDef>
	
	<!-- .36 Caliber -->
	
	<CombatExtended.AmmoSetDef>
		<defName>AmmoSet_MusketBall_36Caliber_Pistol</defName>
		<label>.36 caliber ball</label>
		<ammoTypes>
			<Ammo_MusketBall>Bullet_36CaliberBall_Pistol</Ammo_MusketBall>
		</ammoTypes>
	</CombatExtended.AmmoSetDef>

	<ThingDef ParentName="MusketBallBullet">
		<defName>Bullet_36CaliberBall_Pistol</defName>
		<label>.36 caliber ball</label>
		<projectile Class="CombatExtended.ProjectilePropertiesCE">
			<speed>45</speed>	
			<damageAmountBase>9</damageAmountBase>		
			<armorPenetrationSharp>3</armorPenetrationSharp>
			<armorPenetrationBlunt>8.8</armorPenetrationBlunt>				
		</projectile>
	</ThingDef>
	
	<!-- .41 Caliber -->
	
	<CombatExtended.AmmoSetDef>
		<defName>AmmoSet_MusketBall_41Caliber_Pistol</defName>
		<label>.41 caliber ball</label>
		<ammoTypes>
			<Ammo_MusketBall>Bullet_41CaliberBall_Pistol</Ammo_MusketBall>
		</ammoTypes>
	</CombatExtended.AmmoSetDef>

	<ThingDef ParentName="MusketBallBullet">
		<defName>Bullet_41CaliberBall_Pistol</defName>
		<label>.41 caliber ball</label>
		<projectile Class="CombatExtended.ProjectilePropertiesCE">
			<speed>45</speed>	
			<damageAmountBase>9</damageAmountBase>		
			<armorPenetrationSharp>3</armorPenetrationSharp>
			<armorPenetrationBlunt>9</armorPenetrationBlunt>				
		</projectile>
	</ThingDef>

	<!-- .44 Caliber -->
	
	<CombatExtended.AmmoSetDef>
		<defName>AmmoSet_MusketBall_44Caliber_Pistol</defName>
		<label>.44 caliber ball</label>
		<ammoTypes>
			<Ammo_MusketBall>Bullet_44CaliberBall_Pistol</Ammo_MusketBall>
		</ammoTypes>
	</CombatExtended.AmmoSetDef>

	<ThingDef ParentName="MusketBallBullet">
		<defName>Bullet_44CaliberBall_Pistol</defName>
		<label>.44 caliber ball</label>
		<projectile Class="CombatExtended.ProjectilePropertiesCE">
			<speed>45</speed>	
			<damageAmountBase>13</damageAmountBase>		
			<armorPenetrationSharp>3.4</armorPenetrationSharp>
			<armorPenetrationBlunt>16</armorPenetrationBlunt>				
		</projectile>
	</ThingDef>
	
	<!-- .46 Caliber -->
	
	<CombatExtended.AmmoSetDef>
		<defName>AmmoSet_MusketBall_46Caliber</defName>
		<label>.46 caliber ball</label>
		<ammoTypes>
			<Ammo_MusketBall>Bullet_46CaliberBall</Ammo_MusketBall>
		</ammoTypes>
	</CombatExtended.AmmoSetDef>

	<ThingDef ParentName="MusketBallBullet">
		<defName>Bullet_46CaliberBall</defName>
		<label>.46 caliber ball</label>
		<projectile Class="CombatExtended.ProjectilePropertiesCE">
			<speed>50</speed>	
			<damageAmountBase>16</damageAmountBase>		
			<armorPenetrationSharp>3.3</armorPenetrationSharp>
			<armorPenetrationBlunt>18</armorPenetrationBlunt>				
		</projectile>
	</ThingDef>
	
	<!-- .47 Caliber -->
	
	<CombatExtended.AmmoSetDef>
		<defName>AmmoSet_MusketBall_47Caliber</defName>
		<label>.47 caliber ball</label>
		<ammoTypes>
			<Ammo_MusketBall>Bullet_47CaliberBall</Ammo_MusketBall>
		</ammoTypes>
	</CombatExtended.AmmoSetDef>

	<ThingDef ParentName="MusketBallBullet">
		<defName>Bullet_47CaliberBall</defName>
		<label>.47 caliber ball</label>
		<projectile Class="CombatExtended.ProjectilePropertiesCE">
			<speed>50</speed>	
			<damageAmountBase>18</damageAmountBase>		
			<armorPenetrationSharp>3.3</armorPenetrationSharp>
			<armorPenetrationBlunt>19</armorPenetrationBlunt>				
		</projectile>
	</ThingDef>
	
	<!-- .50 Caliber -->
	
	<CombatExtended.AmmoSetDef>
		<defName>AmmoSet_MusketBall_50Caliber</defName>
		<label>.50 caliber ball</label>
		<ammoTypes>
			<Ammo_MusketBall>Bullet_50CaliberBall</Ammo_MusketBall>
		</ammoTypes>
	</CombatExtended.AmmoSetDef>

	<ThingDef ParentName="MusketBallBullet">
		<defName>Bullet_50CaliberBall</defName>
		<label>.50 caliber ball</label>
		<projectile Class="CombatExtended.ProjectilePropertiesCE">
			<speed>50</speed>	
			<damageAmountBase>17</damageAmountBase>		
			<armorPenetrationSharp>3.35</armorPenetrationSharp>
			<armorPenetrationBlunt>19.57</armorPenetrationBlunt>				
		</projectile>
	</ThingDef>
	
	<!-- .52 Caliber -->
	
	<CombatExtended.AmmoSetDef>
		<defName>AmmoSet_MusketBall_52Caliber</defName>
		<label>.52 caliber ball</label>
		<ammoTypes>
			<Ammo_MusketBall>Bullet_52CaliberBall</Ammo_MusketBall>
		</ammoTypes>
	</CombatExtended.AmmoSetDef>

	<ThingDef ParentName="MusketBallBullet">
		<defName>Bullet_52CaliberBall</defName>
		<label>.52 caliber ball</label>
		<projectile Class="CombatExtended.ProjectilePropertiesCE">
			<speed>50</speed>	
			<damageAmountBase>17</damageAmountBase>		
			<armorPenetrationSharp>3.43</armorPenetrationSharp>
			<armorPenetrationBlunt>19</armorPenetrationBlunt>				
		</projectile>
	</ThingDef>

	<!-- .53 Caliber -->
	
	<CombatExtended.AmmoSetDef>
		<defName>AmmoSet_MusketBall_53Caliber</defName>
		<label>.53 caliber ball</label>
		<ammoTypes>
			<Ammo_MusketBall>Bullet_53CaliberBall</Ammo_MusketBall>
		</ammoTypes>
	</CombatExtended.AmmoSetDef>

	<ThingDef ParentName="MusketBallBullet">
		<defName>Bullet_53CaliberBall</defName>
		<label>.53 caliber ball</label>
		<projectile Class="CombatExtended.ProjectilePropertiesCE">
			<speed>50</speed>	
			<damageAmountBase>17</damageAmountBase>		
			<armorPenetrationSharp>3.45</armorPenetrationSharp>
			<armorPenetrationBlunt>20</armorPenetrationBlunt>				
		</projectile>
	</ThingDef>
	
	<!-- .54 Caliber -->
	
	<CombatExtended.AmmoSetDef>
		<defName>AmmoSet_MusketBall_54Caliber</defName>
		<label>.54 caliber ball</label>
		<ammoTypes>
			<Ammo_MusketBall>Bullet_54CaliberBall</Ammo_MusketBall>
		</ammoTypes>
	</CombatExtended.AmmoSetDef>

	<ThingDef ParentName="MusketBallBullet">
		<defName>Bullet_54CaliberBall</defName>
		<label>.54 caliber ball</label>
		<projectile Class="CombatExtended.ProjectilePropertiesCE">
			<speed>50</speed>	
			<damageAmountBase>18</damageAmountBase>		
			<armorPenetrationSharp>3.5</armorPenetrationSharp>
			<armorPenetrationBlunt>20</armorPenetrationBlunt>				
		</projectile>
	</ThingDef>
	
	<!-- .55 Caliber -->
	
	<CombatExtended.AmmoSetDef>
		<defName>AmmoSet_MusketBall_55Caliber</defName>
		<label>.55 caliber ball</label>
		<ammoTypes>
			<Ammo_MusketBall>Bullet_55CaliberBall</Ammo_MusketBall>
		</ammoTypes>
	</CombatExtended.AmmoSetDef>

	<ThingDef ParentName="MusketBallBullet">
		<defName>Bullet_55CaliberBall</defName>
		<label>.55 caliber ball</label>
		<projectile Class="CombatExtended.ProjectilePropertiesCE">
			<speed>50</speed>	
			<damageAmountBase>18</damageAmountBase>		
			<armorPenetrationSharp>3.55</armorPenetrationSharp>
			<armorPenetrationBlunt>20</armorPenetrationBlunt>				
		</projectile>
	</ThingDef>
	
	<!-- .58 Caliber -->
	
	<CombatExtended.AmmoSetDef>
		<defName>AmmoSet_MusketBall_58Caliber</defName>
		<label>.58 caliber ball</label>
		<ammoTypes>
			<Ammo_MusketBall>Bullet_58CaliberBall</Ammo_MusketBall>
		</ammoTypes>
	</CombatExtended.AmmoSetDef>

	<ThingDef ParentName="MusketBallBullet">
		<defName>Bullet_58CaliberBall</defName>
		<label>.58 caliber ball</label>
		<projectile Class="CombatExtended.ProjectilePropertiesCE">
			<speed>50</speed>	
			<damageAmountBase>18</damageAmountBase>		
			<armorPenetrationSharp>3.65</armorPenetrationSharp>
			<armorPenetrationBlunt>21</armorPenetrationBlunt>				
		</projectile>
	</ThingDef>
	
	<!-- .62 Caliber -->
	
	<CombatExtended.AmmoSetDef>
		<defName>AmmoSet_MusketBall_62Caliber</defName>
		<label>.62 caliber ball</label>
		<ammoTypes>
			<Ammo_MusketBall>Bullet_62CaliberBall</Ammo_MusketBall>
		</ammoTypes>
	</CombatExtended.AmmoSetDef>

	<ThingDef ParentName="MusketBallBullet">
		<defName>Bullet_62CaliberBall</defName>
		<label>.62 caliber ball</label>
		<projectile Class="CombatExtended.ProjectilePropertiesCE">
			<speed>50</speed>	
			<damageAmountBase>18</damageAmountBase>		
			<armorPenetrationSharp>3.68</armorPenetrationSharp>
			<armorPenetrationBlunt>21</armorPenetrationBlunt>				
		</projectile>
	</ThingDef>
	
	<!-- .65 Caliber -->
	
	<CombatExtended.AmmoSetDef>
		<defName>AmmoSet_MusketBall_65Caliber</defName>
		<label>.65 caliber ball</label>
		<ammoTypes>
			<Ammo_MusketBall>Bullet_65CaliberBall</Ammo_MusketBall>
		</ammoTypes>
	</CombatExtended.AmmoSetDef>

	<ThingDef ParentName="MusketBallBullet">
		<defName>Bullet_65CaliberBall</defName>
		<label>.65 caliber ball</label>
		<projectile Class="CombatExtended.ProjectilePropertiesCE">
			<speed>50</speed>	
			<damageAmountBase>18</damageAmountBase>		
			<armorPenetrationSharp>3.7</armorPenetrationSharp>
			<armorPenetrationBlunt>21</armorPenetrationBlunt>				
		</projectile>
	</ThingDef>
	
	<!-- .69 Caliber -->
	
	<CombatExtended.AmmoSetDef>
		<defName>AmmoSet_MusketBall_69Caliber</defName>
		<label>.69 caliber ball</label>
		<ammoTypes>
			<Ammo_MusketBall>Bullet_69CaliberBall</Ammo_MusketBall>
		</ammoTypes>
	</CombatExtended.AmmoSetDef>

	<ThingDef ParentName="MusketBallBullet">
		<defName>Bullet_69CaliberBall</defName>
		<label>.69 caliber ball</label>
		<projectile Class="CombatExtended.ProjectilePropertiesCE">
			<speed>50</speed>	
			<damageAmountBase>19</damageAmountBase>		
			<armorPenetrationSharp>3.7</armorPenetrationSharp>
			<armorPenetrationBlunt>21.5</armorPenetrationBlunt>				
		</projectile>
	</ThingDef>
	
	<!-- .75 Caliber -->
	
	<CombatExtended.AmmoSetDef>
		<defName>AmmoSet_MusketBall_75Caliber</defName>
		<label>.75 caliber ball</label>
		<ammoTypes>
			<Ammo_MusketBall>Bullet_75CaliberBall</Ammo_MusketBall>
		</ammoTypes>
	</CombatExtended.AmmoSetDef>

	<ThingDef ParentName="MusketBallBullet">
		<defName>Bullet_75CaliberBall</defName>
		<label>.75 caliber ball</label>
		<projectile Class="CombatExtended.ProjectilePropertiesCE">
			<speed>50</speed>	
			<damageAmountBase>19</damageAmountBase>		
			<armorPenetrationSharp>3.75</armorPenetrationSharp>
			<armorPenetrationBlunt>22</armorPenetrationBlunt>				
		</projectile>
	</ThingDef>
 
	
</Defs>