<?xml version="1.0" encoding="utf-8" ?>
<Defs>

	<ThingDef MayRequire="cgf1.gunsgalore.magnum.i" ParentName="BaseBullet">
		<defName>CGF1_MWP_Bullet_500Bushwhacker_Pistol</defName>
		<label>.500 Bushwhacker</label>
		<graphicData>
			<texPath>Things/Projectile/Bullet_Small</texPath>
			<graphicClass>Graphic_Single</graphicClass>
		</graphicData>
		<projectile>
			<damageDef>Bullet</damageDef>
			<damageAmountBase>30</damageAmountBase>
			<speed>73</speed>
			<stoppingPower>3.5</stoppingPower>
		</projectile>
	</ThingDef>
	
</Defs>